my_module/__init__.py
my_module/add.py
my_module/divide.py
my_module/modulo.py
my_module/multiply.py
my_module/power.py
my_module/subtract.py
my_module_r3ap3rpy-0.0.0.2.dist-info/LICENSE
my_module_r3ap3rpy-0.0.0.2.dist-info/METADATA
my_module_r3ap3rpy-0.0.0.2.dist-info/WHEEL
my_module_r3ap3rpy-0.0.0.2.dist-info/top_level.txt
my_module_r3ap3rpy-0.0.0.2.dist-info/RECORD
