Metadata-Version: 2.1
Name: my-module-r3ap3rpy
Version: 0.0.0.2
Summary: Egy szimpla python module!
Home-page: UNKNOWN
Author: Dani
Author-email: r3ap3rpy@gmail.com
License: UNKNOWN
Platform: UNKNOWN
Classifier: Programming Language :: Python :: 3
Classifier: License :: OSI Approved :: MIT License
Classifier: Operating System :: OS Independent
Requires-Python: >=3.8.6
